<annotation>
	<folder>500</folder>
	<filename>IMG-20200817-WA0374.jpg</filename>
	<path>C:\Users\PC-4\Desktop\Indian-master\training\500\IMG-20200817-WA0374.jpg</path>
	<source>
		<database>Unknown</database>
	</source>
	<size>
		<width>1152</width>
		<height>864</height>
		<depth>3</depth>
	</size>
	<segmented>0</segmented>
	<object>
		<name>500</name>
		<pose>Unspecified</pose>
		<truncated>0</truncated>
		<difficult>0</difficult>
		<bndbox>
			<xmin>413</xmin>
			<ymin>403</ymin>
			<xmax>472</xmax>
			<ymax>489</ymax>
		</bndbox>
	</object>
	<object>
		<name>500</name>
		<pose>Unspecified</pose>
		<truncated>0</truncated>
		<difficult>0</difficult>
		<bndbox>
			<xmin>730</xmin>
			<ymin>410</ymin>
			<xmax>813</xmax>
			<ymax>449</ymax>
		</bndbox>
	</object>
</annotation>
